ldmodel/__init__.py
ldmodel/model.py
ldmodel-0.1.0.dist-info/LICENSE
ldmodel-0.1.0.dist-info/METADATA
ldmodel-0.1.0.dist-info/WHEEL
ldmodel-0.1.0.dist-info/top_level.txt
ldmodel-0.1.0.dist-info/RECORD
